nbgv_python/__init__.py
nbgv_python/cli.py
nbgv_python/command.py
nbgv_python/config.py
nbgv_python/errors.py
nbgv_python/hatch_plugin.py
nbgv_python/models.py
nbgv_python/runner.py
nbgv_python/templating.py
nbgv_python/versioning.py
nbgv_python/writer.py
nbgv_python-2.0.0.dist-info/METADATA
nbgv_python-2.0.0.dist-info/WHEEL
nbgv_python-2.0.0.dist-info/entry_points.txt
nbgv_python-2.0.0.dist-info/RECORD
