Metadata-Version: 2.4
Name: nbgv-python
Version: 2.0.0
Summary: Python wrapper around the Nerdbank.GitVersioning CLI
Project-URL: Repository, https://github.com/hcoona/three
Project-URL: Issues, https://github.com/hcoona/three/issues
Project-URL: Documentation, https://github.com/hcoona/three/blob/main/src/public/lib/nbgv-python/README.md
Project-URL: Changelog, https://github.com/hcoona/three/blob/main/src/public/lib/nbgv-python/CHANGELOG.md
Author-email: Shuai Zhang <zhangshuai.ustc@gmail.com>
License: LGPL-3.0-or-later WITH LGPL-3.0-linking-exception
Keywords: hatch,nbgv,versioning
Classifier: Framework :: Hatch
Classifier: License :: OSI Approved :: GNU Lesser General Public License v3 or later (LGPLv3+)
Classifier: Operating System :: OS Independent
Classifier: Programming Language :: Python :: 3
Classifier: Programming Language :: Python :: 3.12
Classifier: Programming Language :: Python :: 3.13
Requires-Python: >=3.12
Requires-Dist: packaging>=24.0
